MANIFEST.in
README.rst
setup.cfg
setup.py
cmdbot_evented/__init__.py
cmdbot_evented/configs.py
cmdbot_evented/core.py
cmdbot_evented/decorators.py
cmdbot_evented.egg-info/PKG-INFO
cmdbot_evented.egg-info/SOURCES.txt
cmdbot_evented.egg-info/dependency_links.txt
cmdbot_evented.egg-info/entry_points.txt
cmdbot_evented.egg-info/not-zip-safe
cmdbot_evented.egg-info/requires.txt
cmdbot_evented.egg-info/top_level.txt
locale/fr/LC_MESSAGES/cmdbot.mo