Metadata-Version: 1.0
Name: cmdbot-evented
Version: 0.1.0dev
Summary: An IRC Bot with a `cmd` attitude
Home-page: https://github.com/kyleterry/cmdbot-evented/
Author: Bruno Bord modified by Kyle Terry
Author-email: bruno@jehaisleprintemps.net
License: Public Domain (WTFPL)
Platform: UNKNOWN
